simple_ddl_parser_2/__init__.py
simple_ddl_parser_2/cli.py
simple_ddl_parser_2/ddl_parser.py
simple_ddl_parser_2/dialects/__init__.py
simple_ddl_parser_2/dialects/athena.py
simple_ddl_parser_2/dialects/bigquery.py
simple_ddl_parser_2/dialects/hql.py
simple_ddl_parser_2/dialects/ibm.py
simple_ddl_parser_2/dialects/mssql.py
simple_ddl_parser_2/dialects/mysql.py
simple_ddl_parser_2/dialects/oracle.py
simple_ddl_parser_2/dialects/psql.py
simple_ddl_parser_2/dialects/redshift.py
simple_ddl_parser_2/dialects/snowflake.py
simple_ddl_parser_2/dialects/spark_sql.py
simple_ddl_parser_2/dialects/sql.py
simple_ddl_parser_2/exception.py
simple_ddl_parser_2/output/base_data.py
simple_ddl_parser_2/output/core.py
simple_ddl_parser_2/output/dialects.py
simple_ddl_parser_2/output/table_data.py
simple_ddl_parser_2/parser.py
simple_ddl_parser_2/parsetab.py
simple_ddl_parser_2/tokens.py
simple_ddl_parser_2/utils.py
simple_ddl_parser_2-0.1.5.dist-info/LICENSE
simple_ddl_parser_2-0.1.5.dist-info/METADATA
simple_ddl_parser_2-0.1.5.dist-info/WHEEL
simple_ddl_parser_2-0.1.5.dist-info/entry_points.txt
simple_ddl_parser_2-0.1.5.dist-info/RECORD
