Metadata-Version: 2.1
Name: simple-ddl-parser-2
Version: 0.1.5
Summary: This is fork project from https://github.com/xnuinside/simple-ddl-parser
Home-page: https://github.com/nhatndq-nals/simple-ddl-parser-2
License: MIT
Keywords: python,package
Author: NhatNDQ
Author-email: nhatndq-nals@nal.vn
Requires-Python: >=3.6,<4.0
Classifier: License :: OSI Approved :: MIT License
Classifier: Programming Language :: PL/SQL
Classifier: Programming Language :: Python :: 3
Classifier: Programming Language :: Python :: 3.6
Classifier: Programming Language :: Python :: 3.7
Classifier: Programming Language :: Python :: 3.8
Classifier: Programming Language :: Python :: 3.9
Classifier: Programming Language :: Python :: 3.10
Classifier: Programming Language :: Python :: 3.11
Classifier: Programming Language :: Python :: 3.12
Classifier: Programming Language :: SQL
Classifier: Topic :: Software Development
Classifier: Topic :: Software Development :: Libraries
Classifier: Topic :: Software Development :: Libraries :: Python Modules
Classifier: Topic :: Utilities
Requires-Dist: dataclasses (==0.8) ; python_version >= "3.6" and python_version < "3.7"
Requires-Dist: ply (>=3.11,<4.0)
Project-URL: Repository, https://github.com/nhatndq-nals/simple-ddl-parser-2
